sarus_proxy/__init__.py
sarus_proxy/api_client.py
sarus_proxy/api_response.py
sarus_proxy/configuration.py
sarus_proxy/exceptions.py
sarus_proxy/py.typed
sarus_proxy/rest.py
sarus_proxy/api/__init__.py
sarus_proxy/api/default_api.py
sarus_proxy/api/events_api.py
sarus_proxy/api/login_api.py
sarus_proxy/api/mistral_api.py
sarus_proxy/api/openai_api.py
sarus_proxy/api/settings_api.py
sarus_proxy/api/users_api.py
sarus_proxy/api/utils_api.py
sarus_proxy/models/__init__.py
sarus_proxy/models/body_create_user_open_api_v1_users_open_post.py
sarus_proxy/models/body_reset_password_api_v1_reset_password_post.py
sarus_proxy/models/body_update_user_me_api_v1_users_me_put.py
sarus_proxy/models/client_id.py
sarus_proxy/models/client_secret.py
sarus_proxy/models/email.py
sarus_proxy/models/event.py
sarus_proxy/models/event_create.py
sarus_proxy/models/full_name.py
sarus_proxy/models/grant_type.py
sarus_proxy/models/http_validation_error.py
sarus_proxy/models/id.py
sarus_proxy/models/is_active.py
sarus_proxy/models/is_superuser.py
sarus_proxy/models/msg.py
sarus_proxy/models/parent_id.py
sarus_proxy/models/password.py
sarus_proxy/models/response_read_setting.py
sarus_proxy/models/setting.py
sarus_proxy/models/setting_create.py
sarus_proxy/models/timestamp.py
sarus_proxy/models/token.py
sarus_proxy/models/user.py
sarus_proxy/models/user_create.py
sarus_proxy/models/user_update.py
sarus_proxy/models/validation_error.py
sarus_proxy/models/validation_error_loc_inner.py
sarus_proxy-1.0.11.dist-info/METADATA
sarus_proxy-1.0.11.dist-info/WHEEL
sarus_proxy-1.0.11.dist-info/top_level.txt
sarus_proxy-1.0.11.dist-info/RECORD
